baaya/__init__.py
baaya/__main__.py
baaya/baaya.py
baaya/main.py
baaya/stats.py
baaya/test_baaya.py
baaya-0.0.3.dist-info/DESCRIPTION.rst
baaya-0.0.3.dist-info/METADATA
baaya-0.0.3.dist-info/RECORD
baaya-0.0.3.dist-info/WHEEL
baaya-0.0.3.dist-info/entry_points.txt
baaya-0.0.3.dist-info/metadata.json
baaya-0.0.3.dist-info/top_level.txt
